swm/__init__.py
swm/__version__.py
swm/cli.py
swm/test_edit_file.py
swm/test_parse_scrcpy_app_list_output.py
swm_android-0.3.3.2.1.dist-info/licenses/LICENSE
swm_android-0.3.3.2.1.dist-info/METADATA
swm_android-0.3.3.2.1.dist-info/WHEEL
swm_android-0.3.3.2.1.dist-info/entry_points.txt
swm_android-0.3.3.2.1.dist-info/top_level.txt
swm_android-0.3.3.2.1.dist-info/RECORD
