Metadata-Version: 2.4
Name: swm-android
Version: 0.3.3.2.1
Summary: Android window manager using Scrcpy on PC
Home-page: https://github.com/james4ever0/swm
Author: James Brown
Author-email: randomvoidmail@foxmail.com
License: MIT
Classifier: License :: OSI Approved :: The Unlicense (Unlicense)
Classifier: Programming Language :: Python
Classifier: Programming Language :: Python :: 3
Classifier: Programming Language :: Python :: 3.6
Classifier: Programming Language :: Python :: Implementation :: CPython
Classifier: Programming Language :: Python :: Implementation :: PyPy
Requires-Python: >=3.6.0
License-File: LICENSE
Requires-Dist: fuzzywuzzy
Requires-Dist: omegaconf
Requires-Dist: docopt
Requires-Dist: requests
Requires-Dist: PyYAML
Requires-Dist: pandas
Requires-Dist: tinydb
Requires-Dist: pyperclip
Requires-Dist: pyautogui
Requires-Dist: psutil
Requires-Dist: textual
Requires-Dist: pillow
Requires-Dist: filelock
Requires-Dist: ted-editor==0.1.2
Provides-Extra: speedup
Requires-Dist: python-Levenshtein; extra == "speedup"
Dynamic: author
Dynamic: author-email
Dynamic: classifier
Dynamic: description
Dynamic: description-content-type
Dynamic: home-page
Dynamic: license
Dynamic: license-file
Dynamic: provides-extra
Dynamic: requires-dist
Dynamic: requires-python
Dynamic: summary
